emailgen/__init__.py
emailgen/email.py
emailgen/generator.py
emailgen/themes.py
emailgen-0.1.1.dist-info/DESCRIPTION.rst
emailgen-0.1.1.dist-info/METADATA
emailgen-0.1.1.dist-info/RECORD
emailgen-0.1.1.dist-info/WHEEL
emailgen-0.1.1.dist-info/metadata.json
emailgen-0.1.1.dist-info/top_level.txt
