Metadata-Version: 2.0
Name: emailgen
Version: 0.1.1
Summary: Email Generation for Humans
Home-page: https://github.com/finnesota/emailgen
Author: Finnesota LLC
Author-email: info@finnesota.com
License: Apache
Keywords: email,generation,html,SaaS,transactional
Platform: UNKNOWN
Classifier: Development Status :: 4 - Beta
Classifier: Environment :: Web Environment
Classifier: Intended Audience :: Developers
Classifier: Natural Language :: English
Classifier: Programming Language :: Python :: 2.7
Classifier: Programming Language :: Python :: 3.4
Classifier: Programming Language :: Python :: 3.5
Classifier: Programming Language :: Python :: 3.6
Classifier: Topic :: Software Development :: Libraries
Requires-Dist: jinja2
Requires-Dist: markdown2
